[
    {
        "type": "yes-no",
        "header": "音楽経験などに関するアンケート",
        "text":
            [
                "あなたは，高校や大学などで音楽に関わる分野(作曲, 楽器演奏, 音楽環境, 音楽情報処理など)を専攻していますか? または，専攻していましたか?"
            ]
    },
    {
        "type": "mos1",
        "header": "楽曲評価（その1）",
        "music_id": 0
    },
    {
        "type": "introduction",
        "header": "楽曲評価（その2）",
        "text":
            [
                "ここでは，楽曲の評価を行います．",
                "人によって作られた楽曲，または，コンピュータによって作られた楽曲がランダムに呈示されます．",
                "楽曲を聴いた後，「音楽性」「自然さ」「楽曲区間の境目の明瞭さ」「楽曲区間内での統一感」の4つの観点から，それぞれ5点満点で評価してください．",
                "ここでの楽曲区間とは，Aメロやサビなど，類似したメロディーが現れる一部区間のことを指します．",
                "楽曲は何度聴き直しても構いません．"
            ]
    },
    {
        "type": "introduction",
        "header": "終了",
        "text": [
            "これで実験は終了です．ご協力ありがとうございました．",
            "「回答を送信」を押してください．"
        ]
    }
]
